setup.py
scraper/__init__.py
scraper/models/__init__.py
scraper/models/profile.py
scraper/repository/__init__.py
scraper/repository/mongodb/__init__.py
scraper/repository/mongodb/mongodb.py
scraper/repository/mongodb/orm.py
scraper/repository/mongodb/profile.py
webscraper_core.egg-info/PKG-INFO
webscraper_core.egg-info/SOURCES.txt
webscraper_core.egg-info/dependency_links.txt
webscraper_core.egg-info/requires.txt
webscraper_core.egg-info/top_level.txt