Metadata-Version: 1.1
Name: webscraper-core
Version: 0.1.1
Summary: Just an easy way to get Facebook and Twitter Profiles
Home-page: https://github.com/victorpantoja/scraper
Author: Victor Pantoja
Author-email: victor.pantoja@gmail.com
License: MIT
Keywords: twitter facebook profile scrap
Platform: UNKNOWN
Classifier: Development Status :: 4 - Beta
Classifier: Intended Audience :: Developers
Classifier: Programming Language :: Python
